setup.py
mhelper/__test__.py
mhelper/accuracy_helper.py
mhelper/ansi.py
mhelper/ansi_format_helper.py
mhelper/ansi_helper.py
mhelper/arg_parser.py
mhelper/array_helper.py
mhelper/async_helper.py
mhelper/batch_lists.py
mhelper/bio_helper.py
mhelper/bio_query_helper.py
mhelper/cache_helper.py
mhelper/cli_helper.py
mhelper/cli_parser.py
mhelper/colours.py
mhelper/comment_helper.py
mhelper/component_helper.py
mhelper/console_helper.py
mhelper/data_store.py
mhelper/debug_helper.py
mhelper/disk_cache.py
mhelper/dispatch_helper.py
mhelper/disposal_helper.py
mhelper/documentation_helper.py
mhelper/emoji_helper.py
mhelper/enum_helper.py
mhelper/event_helper.py
mhelper/exception_formatter.py
mhelper/exception_helper.py
mhelper/exception_hooks.py
mhelper/exception_recorder.py
mhelper/exception_recorder_exe.py
mhelper/file_helper.py
mhelper/generics_helper.py
mhelper/html_helper.py
mhelper/io_helper.py
mhelper/ipc_helper.py
mhelper/json_helper.py
mhelper/jupyter_helper.py
mhelper/lambda_helper.py
mhelper/location_helper.py
mhelper/lock_helper.py
mhelper/markdown_helper.py
mhelper/maths_helper.py
mhelper/misc_helper.py
mhelper/module_helper.py
mhelper/multiprocessing_helper.py
mhelper/notebook_helper.py
mhelper/output_helper.py
mhelper/password_helper.py
mhelper/peptide_helper.py
mhelper/pip_helper.py
mhelper/print_helper.py
mhelper/progress_helper.py
mhelper/property_helper.py
mhelper/proxy_helper.py
mhelper/qt_resource_objects.py
mhelper/quickformatter.py
mhelper/reflection_helper.py
mhelper/rst_helper.py
mhelper/sequential_io.py
mhelper/serialisable.py
mhelper/settings_helper.py
mhelper/setup_helper.py
mhelper/special_types.py
mhelper/specific_locations.py
mhelper/sql_helper.py
mhelper/state_helper.py
mhelper/string_helper.py
mhelper/string_parser.py
mhelper/subprocess_helper.py
mhelper/svg_helper.py
mhelper/system_event_helper_check.py
mhelper/tcp_server_helper.py
mhelper/testing_helper.py
mhelper/users_db_helper.py
mhelper/utf_helper.py
mhelper/utf_table.py
mhelper.egg-info/PKG-INFO
mhelper.egg-info/SOURCES.txt
mhelper.egg-info/dependency_links.txt
mhelper.egg-info/requires.txt
mhelper.egg-info/top_level.txt
