Metadata-Version: 2.1
Name: mhelper
Version: 1.0.1.437
Summary: Includes a collection of utility functions.
Home-page: https://bitbucket.org/mjr129/mhelper
Author: Martin Rusilowicz
License: https://www.gnu.org/licenses/agpl-3.0.html
Requires-Python: >=3.6
Provides-Extra: everything
Requires-Dist: jsonpickle; extra == "everything"
Requires-Dist: PyQt5; extra == "everything"
Requires-Dist: mistune; extra == "everything"
Provides-Extra: deprecated
Requires-Dist: py-flags; extra == "deprecated"
